cursofiapHiran/__init__.py
cursofiapHiran/core.py
cursofiaphiran_package-1.0.0.dist-info/METADATA
cursofiaphiran_package-1.0.0.dist-info/WHEEL
cursofiaphiran_package-1.0.0.dist-info/top_level.txt
cursofiaphiran_package-1.0.0.dist-info/RECORD
